MANIFEST.in
setup.py
deployment/appengine/dpxdt/__init__.py
deployment/appengine/dpxdt/constants.py
deployment/appengine/dpxdt/runserver.py
deployment/appengine/dpxdt/runworker.py
deployment/worker/dpxdt/__init__.py
deployment/worker/dpxdt/constants.py
deployment/worker/dpxdt/runserver.py
deployment/worker/dpxdt/runworker.py
dpxdt/__init__.py
dpxdt/constants.py
dpxdt/runserver.py
dpxdt/runworker.py
dpxdt.egg-info/PKG-INFO
dpxdt.egg-info/SOURCES.txt
dpxdt.egg-info/dependency_links.txt
dpxdt.egg-info/entry_points.txt
dpxdt.egg-info/requires.txt
dpxdt.egg-info/top_level.txt
dpxdt/client/__init__.py
dpxdt/client/__init__.pyc
dpxdt/client/capture.js
dpxdt/client/capture_worker.py
dpxdt/client/capture_worker.pyc
dpxdt/client/fetch_worker.py
dpxdt/client/fetch_worker.pyc
dpxdt/client/pdiff_worker.py
dpxdt/client/pdiff_worker.pyc
dpxdt/client/process_worker.py
dpxdt/client/process_worker.pyc
dpxdt/client/queue_worker.py
dpxdt/client/queue_worker.pyc
dpxdt/client/release_worker.py
dpxdt/client/release_worker.pyc
dpxdt/client/timer_worker.py
dpxdt/client/timer_worker.pyc
dpxdt/client/workers.py
dpxdt/client/workers.pyc
dpxdt/server/__init__.py
dpxdt/server/api.py
dpxdt/server/auth.py
dpxdt/server/emails.py
dpxdt/server/forms.py
dpxdt/server/frontend.py
dpxdt/server/models.py
dpxdt/server/operations.py
dpxdt/server/signals.py
dpxdt/server/utils.py
dpxdt/server/work_queue.py
dpxdt/server/work_queue_handlers.py
dpxdt/tools/__init__.py
dpxdt/tools/diff_my_images.py
dpxdt/tools/diff_my_urls.py
dpxdt/tools/flags.py
dpxdt/tools/local_pdiff.py
dpxdt/tools/site_diff.py
dpxdt/tools/url_pair_diff.py