Metadata-Version: 1.1
Name: dpxdt
Version: 0.1.3
Summary: Screenshot diff tool
Home-page: https://github.com/bslatkin/dpxdt/
Author: Brett Slatkin
Author-email: brett@haxor.com
License: UNKNOWN
Platform: UNKNOWN
Classifier: Environment :: Console
Classifier: Environment :: Web Environment
Classifier: Framework :: Flask
Classifier: Development Status :: 3 - Alpha
Classifier: Intended Audience :: Developers
Classifier: License :: OSI Approved :: Apache Software License
Classifier: Topic :: Software Development :: Version Control
